biotope/__init__.py
biotope/__main__.py
biotope/cli.py
biotope/commands/__init__.py
biotope/commands/add.py
biotope/commands/annotate.py
biotope/commands/build.py
biotope/commands/chat.py
biotope/commands/check_data.py
biotope/commands/commit.py
biotope/commands/config.py
biotope/commands/get.py
biotope/commands/init.py
biotope/commands/log.py
biotope/commands/mv.py
biotope/commands/pull.py
biotope/commands/push.py
biotope/commands/read.py
biotope/commands/status.py
biotope/commands/view.py
biotope/utils.py
biotope/validation.py
biotope-0.5.0.dist-info/LICENSE
biotope-0.5.0.dist-info/METADATA
biotope-0.5.0.dist-info/WHEEL
biotope-0.5.0.dist-info/entry_points.txt
biotope-0.5.0.dist-info/RECORD
