Metadata-Version: 2.3
Name: biotope
Version: 0.5.0
Summary: CLI integration for BioCypher ecosystem packages
License: MIT
Author: Sebastian Lobentanzer
Author-email: sebastian.lobentanzer@gmail.com
Requires-Python: >=3.10,<3.13
Classifier: Development Status :: 2 - Pre-Alpha
Classifier: Intended Audience :: Science/Research
Classifier: License :: OSI Approved :: MIT License
Classifier: Operating System :: OS Independent
Classifier: Programming Language :: Python :: 3
Classifier: Programming Language :: Python :: 3.10
Classifier: Programming Language :: Python :: 3.11
Classifier: Programming Language :: Python :: 3.12
Classifier: Programming Language :: Python :: 3 :: Only
Requires-Dist: PyYAML (>=6.0,<7.0)
Requires-Dist: click (>=8.1.8,<9.0.0)
Requires-Dist: mlcroissant (>=1.0.13,<2.0.0)
Requires-Dist: requests (>=2.31.0,<3.0.0)
Requires-Dist: rich (>=13.9.4,<14.0.0)
Project-URL: Bug Tracker, https://github.com/biocypher/cli/issues
Project-URL: Documentation, https://biocypher.org
Project-URL: Download, https://pypi.org/project/biotope/#files
Project-URL: Homepage, https://github.com/biocypher/cli
Project-URL: Source Code, https://github.com/biocypher/cli
